meta_agent/__init__.py
meta_agent/agent_generator.py
meta_agent/cli.py
meta_agent/config.py
meta_agent/core.py
meta_agent/design/__init__.py
meta_agent/design/analyzer.py
meta_agent/design/guardrail_designer.py
meta_agent/design/output_designer.py
meta_agent/design/tool_designer.py
meta_agent/generation/__init__.py
meta_agent/generation/agent_generator.py
meta_agent/generation/assembler.py
meta_agent/generation/guardrail_generator.py
meta_agent/generation/output_generator.py
meta_agent/generation/runner_generator.py
meta_agent/generation/tool_generator.py
meta_agent/models/__init__.py
meta_agent/models/agent.py
meta_agent/models/code.py
meta_agent/models/design.py
meta_agent/models/guardrail.py
meta_agent/models/implementation.py
meta_agent/models/output.py
meta_agent/models/tool.py
meta_agent/utils/__init__.py
meta_agent/utils/config.py
meta_agent/utils/file_utils.py
meta_agent/utils/string_utils.py
meta_agent/validation/__init__.py
meta_agent/validation/validator.py
danmac_meta_agent-1.0.1.dist-info/LICENSE
danmac_meta_agent-1.0.1.dist-info/METADATA
danmac_meta_agent-1.0.1.dist-info/WHEEL
danmac_meta_agent-1.0.1.dist-info/entry_points.txt
danmac_meta_agent-1.0.1.dist-info/RECORD
