Metadata-Version: 2.3
Name: danmac-meta-agent
Version: 1.0.1
Summary: A meta agent that creates OpenAI Agents SDK agents
License: MIT
Keywords: agent,openai,ai
Author: Meta Agent Developer
Requires-Python: >=3.9,<3.12
Classifier: Development Status :: 4 - Beta
Classifier: Intended Audience :: Developers
Classifier: License :: OSI Approved :: MIT License
Classifier: Operating System :: OS Independent
Classifier: Programming Language :: Python :: 3
Classifier: Programming Language :: Python :: 3.9
Classifier: Programming Language :: Python :: 3.10
Classifier: Programming Language :: Python :: 3.11
Classifier: Programming Language :: Python :: 3.8
Classifier: Topic :: Scientific/Engineering :: Artificial Intelligence
Classifier: Topic :: Software Development :: Libraries :: Python Modules
Requires-Dist: asyncio (>=3.4.3,<4.0.0)
Requires-Dist: beautifulsoup4 (>=4.11.0,<5.0.0)
Requires-Dist: griffe (>=1.5.6,<2.0.0)
Requires-Dist: openai-agents (>=0.0.6,<0.1.0)
Requires-Dist: pydantic (>=2.0.0,<3.0.0)
Requires-Dist: python-dotenv (>=1.0.0,<2.0.0)
Requires-Dist: requests (>=2.28.0,<3.0.0)
Requires-Dist: typing (>=3.7.4.3,<4.0.0)
Project-URL: Documentation, https://github.com/DannyMac180/meta-agent#readme
Project-URL: Homepage, https://github.com/DannyMac180/meta-agent
Project-URL: Repository, https://github.com/DannyMac180/meta-agent
